{
  "symbol": "NVDA",
  "last_updated": "2026-04-30 19:39:52 EDT",
  "dates": [
    "2026-02-02",
    "2026-02-03",
    "2026-02-04",
    "2026-02-05",
    "2026-02-06",
    "2026-02-09",
    "2026-02-10",
    "2026-02-11",
    "2026-02-12",
    "2026-02-13",
    "2026-02-17",
    "2026-02-18",
    "2026-02-19",
    "2026-02-20",
    "2026-02-23",
    "2026-02-24",
    "2026-02-25",
    "2026-02-26",
    "2026-02-27",
    "2026-03-02",
    "2026-03-03",
    "2026-03-04",
    "2026-03-05",
    "2026-03-06",
    "2026-03-09",
    "2026-03-10",
    "2026-03-11",
    "2026-03-12",
    "2026-03-13",
    "2026-03-16",
    "2026-03-17",
    "2026-03-18",
    "2026-03-19",
    "2026-03-20",
    "2026-03-23",
    "2026-03-24",
    "2026-03-25",
    "2026-03-26",
    "2026-03-27",
    "2026-03-30",
    "2026-03-31",
    "2026-04-01",
    "2026-04-02",
    "2026-04-06",
    "2026-04-07",
    "2026-04-08",
    "2026-04-09",
    "2026-04-10",
    "2026-04-13",
    "2026-04-14",
    "2026-04-15",
    "2026-04-16",
    "2026-04-17",
    "2026-04-20",
    "2026-04-21",
    "2026-04-22",
    "2026-04-23",
    "2026-04-24",
    "2026-04-27",
    "2026-04-28",
    "2026-04-29",
    "2026-04-30"
  ],
  "k_data": [
    [
      187.19,
      185.6,
      184.87,
      190.29
    ],
    [
      186.23,
      180.33,
      176.22,
      186.26
    ],
    [
      179.45,
      174.18,
      171.9,
      179.57
    ],
    [
      174.92,
      171.87,
      171.02,
      176.81
    ],
    [
      176.68,
      185.4,
      174.59,
      186.99
    ],
    [
      184.25,
      190.03,
      183.94,
      193.65
    ],
    [
      191.37,
      188.53,
      188.11,
      192.47
    ],
    [
      192.44,
      190.04,
      188.76,
      193.25
    ],
    [
      193.02,
      186.93,
      186.5,
      193.6
    ],
    [
      187.47,
      182.8,
      181.58,
      187.49
    ],
    [
      181.74,
      184.96,
      179.17,
      187.14
    ],
    [
      188.74,
      187.97,
      186.75,
      190.36
    ],
    [
      187.05,
      187.89,
      185.65,
      188.42
    ],
    [
      186.56,
      189.81,
      185.93,
      190.32
    ],
    [
      191.39,
      191.54,
      189.57,
      193.94
    ],
    [
      191.48,
      192.84,
      187.39,
      193.76
    ],
    [
      194.44,
      195.55,
      193.78,
      197.62
    ],
    [
      194.26,
      184.88,
      184.31,
      194.28
    ],
    [
      181.24,
      177.18,
      176.37,
      182.58
    ],
    [
      175.0,
      182.47,
      174.63,
      183.45
    ],
    [
      178.48,
      180.04,
      176.91,
      180.89
    ],
    [
      180.43,
      183.03,
      180.05,
      184.69
    ],
    [
      181.16,
      183.33,
      177.87,
      184.05
    ],
    [
      179.83,
      177.81,
      176.81,
      182.75
    ],
    [
      176.82,
      182.64,
      175.55,
      182.9
    ],
    [
      182.39,
      184.76,
      182.0,
      186.43
    ],
    [
      185.91,
      186.03,
      184.45,
      187.62
    ],
    [
      184.05,
      183.14,
      181.75,
      184.94
    ],
    [
      184.92,
      180.25,
      179.94,
      186.09
    ],
    [
      182.97,
      183.22,
      181.41,
      188.88
    ],
    [
      185.06,
      181.93,
      181.68,
      185.4
    ],
    [
      182.48,
      180.4,
      180.33,
      183.38
    ],
    [
      178.01,
      178.56,
      175.79,
      179.98
    ],
    [
      178.0,
      172.7,
      171.72,
      178.26
    ],
    [
      177.26,
      175.64,
      174.76,
      178.37
    ],
    [
      174.83,
      175.2,
      173.98,
      176.22
    ],
    [
      177.1,
      178.68,
      176.85,
      181.22
    ],
    [
      176.07,
      171.24,
      171.14,
      176.51
    ],
    [
      170.0,
      167.52,
      167.01,
      170.97
    ],
    [
      168.78,
      165.17,
      164.27,
      169.45
    ],
    [
      166.97,
      174.4,
      166.96,
      174.62
    ],
    [
      176.0,
      175.75,
      174.75,
      177.37
    ],
    [
      172.18,
      177.39,
      171.37,
      177.49
    ],
    [
      177.16,
      177.64,
      175.76,
      177.79
    ],
    [
      175.73,
      178.1,
      173.66,
      178.23
    ],
    [
      184.5,
      182.08,
      180.3,
      185.26
    ],
    [
      181.84,
      183.91,
      180.62,
      184.08
    ],
    [
      184.31,
      188.63,
      184.3,
      190.0
    ],
    [
      186.03,
      189.31,
      185.74,
      189.66
    ],
    [
      190.84,
      196.51,
      190.77,
      196.51
    ],
    [
      196.54,
      198.87,
      195.74,
      200.4
    ],
    [
      197.43,
      198.35,
      195.81,
      199.85
    ],
    [
      199.9,
      201.68,
      199.27,
      201.7
    ],
    [
      199.98,
      202.06,
      197.84,
      202.17
    ],
    [
      202.13,
      199.88,
      199.0,
      202.75
    ],
    [
      200.99,
      202.5,
      199.0,
      202.5
    ],
    [
      202.46,
      199.64,
      197.22,
      203.83
    ],
    [
      199.96,
      208.27,
      199.81,
      210.95
    ],
    [
      209.65,
      216.61,
      207.38,
      216.83
    ],
    [
      209.49,
      213.17,
      208.2,
      214.73
    ],
    [
      212.7,
      209.25,
      207.58,
      212.72
    ],
    [
      209.94,
      199.57,
      198.7,
      210.3
    ]
  ],
  "sma_20": [
    null,
    null,
    null,
    null,
    null,
    null,
    null,
    null,
    null,
    null,
    null,
    null,
    null,
    null,
    null,
    null,
    null,
    null,
    null,
    185.54,
    185.26,
    185.4,
    185.85,
    186.15,
    186.01,
    185.75,
    185.62,
    185.28,
    184.95,
    184.97,
    184.82,
    184.44,
    183.97,
    183.12,
    182.32,
    181.44,
    180.59,
    179.91,
    179.43,
    178.56,
    178.28,
    177.92,
    177.62,
    177.61,
    177.39,
    177.25,
    177.15,
    177.42,
    177.87,
    178.54,
    179.38,
    180.28,
    181.44,
    182.91,
    184.12,
    185.48,
    186.53,
    188.38,
    190.84,
    193.24,
    194.98,
    196.17
  ]
}